Metadata-Version: 2.1
Name: odoo-addon-sale_sourced_by_line
Version: 18.0.1.0.1
Requires-Python: >=3.10
Requires-Dist: odoo-addon-sale_procurement_group_by_line==18.0.*
Requires-Dist: odoo==18.0.*
Summary: Multiple warehouse source locations for Sale order
Home-page: https://github.com/OCA/sale-workflow
License: AGPL-3
Author: Camptocamp,ForgeFlow,SerpentCS,Info a tout prix,Odoo Community Association (OCA)
Author-email: support@odoo-community.org
Classifier: Programming Language :: Python
Classifier: Framework :: Odoo
Classifier: Framework :: Odoo :: 18.0
Classifier: License :: OSI Approved :: GNU Affero General Public License v3
